Metadata-Version: 1.1
Name: gpapi-login-fix
Version: 0.4.4
Summary: Unofficial python api for google play
Home-page: https://github.com/worldofprasanna/googleplay-api
Author: NoMore201
Author-email: domenico.iezzi.201@gmail.com
License: GPL3
Download-URL: https://github.com/worldofprasanna/googleplay-api/archive/0.4.4.tar.gz
Platform: UNKNOWN
